discolight/__init__.py
discolight/annotations.py
discolight/augmentor.py
discolight/disco.py
discolight/doc.py
discolight/mkreadme.py
discolight/query.py
discolight/run.py
discolight/augmentations/__init__.py
discolight/augmentations/colortemperature.py
discolight/augmentations/factory.py
discolight/augmentations/gaussiannoise.py
discolight/augmentations/grayscale.py
discolight/augmentations/horizontalflip.py
discolight/augmentations/imagecompression.py
discolight/augmentations/motionblur.py
discolight/augmentations/oneof.py
discolight/augmentations/randomcrop.py
discolight/augmentations/randomeraser.py
discolight/augmentations/randomhsv.py
discolight/augmentations/randomrotate.py
discolight/augmentations/randomscale.py
discolight/augmentations/randomshear.py
discolight/augmentations/randomtranslate.py
discolight/augmentations/resize.py
discolight/augmentations/rotate.py
discolight/augmentations/saltandpeppernoise.py
discolight/augmentations/scale.py
discolight/augmentations/sepia.py
discolight/augmentations/sequence.py
discolight/augmentations/shear.py
discolight/augmentations/translate.py
discolight/augmentations/verticalflip.py
discolight/augmentations/augmentation/__init__.py
discolight/augmentations/augmentation/types.py
discolight/augmentations/bbox_utilities/__init__.py
discolight/augmentations/bbox_utilities/bbox_utilities.py
discolight/augmentations/decorators/__init__.py
discolight/augmentations/decorators/accepts_probs.py
discolight/doc_templates/__init__.py
discolight/doc_templates/discolight.md
discolight/doc_templates/readme.md
discolight/doc_templates/augmentations/MotionBlur.yml
discolight/doc_templates/augmentations/OneOf.yml
discolight/doc_templates/augmentations/RandomCrop.yml
discolight/doc_templates/augmentations/Sequence.yml
discolight/doc_templates/augmentations/__init__.py
discolight/loaders/__init__.py
discolight/loaders/annotation/__init__.py
discolight/loaders/annotation/coco.py
discolight/loaders/annotation/factory.py
discolight-0.4.1.dist-info/LICENSE
discolight-0.4.1.dist-info/METADATA
discolight-0.4.1.dist-info/WHEEL
discolight-0.4.1.dist-info/entry_points.txt
discolight-0.4.1.dist-info/top_level.txt
discolight-0.4.1.dist-info/RECORD
