Metadata-Version: 2.1
Name: discolight
Version: 0.4.1
Summary: Flashy, ravey and state-of-the-art image augmentations to boost the performance of deep convolutional neural networks
Home-page: https://github.com/datature/discolight
Author: Hongnan Gao, Ian Duncan, Keechin Goh
Author-email: discolight@datature.io
License: UNKNOWN
Platform: UNKNOWN
Classifier: Programming Language :: Python :: 3
Classifier: License :: OSI Approved :: MIT License
Classifier: Operating System :: OS Independent
Classifier: Topic :: Scientific/Engineering :: Visualization
Requires-Python: >=3.6, <3.9
Requires-Dist: yamale (>=3.0.1)
Requires-Dist: numpy (>=1.19.0)
Requires-Dist: opencv-python (>=4.3.0.36)
Requires-Dist: scikit-image (>=0.17.2)
Requires-Dist: Pillow (>=7.2.0)
Requires-Dist: Jinja2 (>=2.11.2)
Requires-Dist: tqdm (>=4.47.0)
Requires-Dist: defusedxml (>=0.6.0)
